scuttleSON/__init__.py
scuttleSON-0.0.1.dist-info/LICENSE
scuttleSON-0.0.1.dist-info/METADATA
scuttleSON-0.0.1.dist-info/WHEEL
scuttleSON-0.0.1.dist-info/top_level.txt
scuttleSON-0.0.1.dist-info/RECORD
