Metadata-Version: 2.1
Name: scuttleSON
Version: 0.0.1
Summary: ScuttleSON - shared JSON document editing based on ScuttleSort
Home-page: https://github.com/tschudin/scuttleSON
Author: Christian Tschudin
Author-email: christian.tschudin@unibas.ch
Classifier: Programming Language :: Python :: 3
Classifier: License :: OSI Approved :: MIT License
Classifier: Operating System :: OS Independent
Requires-Python: >=3.7
License-File: LICENSE
